README.md
setup.py
ronda_servable/__init__.py
ronda_servable/device_util.py
ronda_servable/libpytorch_servable.py
ronda_servable/onnx_servable.py
ronda_servable/openvino_servable.py
ronda_servable/pytorch_servable.py
ronda_servable/tensorrt_servable.py
ronda_servable.egg-info/PKG-INFO
ronda_servable.egg-info/SOURCES.txt
ronda_servable.egg-info/dependency_links.txt
ronda_servable.egg-info/requires.txt
ronda_servable.egg-info/top_level.txt